{
    "edges": [
        {
            "id": "3df54ae1-fa41-4ac7-85d5-4badee39215b",
            "source_id": "70447169-9264-41dc-b8e9-50523f8368c1",
            "target_id": "ae3f0c7f-9f69-4cab-9db3-3b9c46f56e09"
        },
        {
            "id": "64430e6e-1300-4623-9b89-3c014587f7ae",
            "source_id": "f129934f-53d2-49f6-8feb-9afaff9aabcf",
            "target_id": "70447169-9264-41dc-b8e9-50523f8368c1"
        },
        {
            "id": "1aae6f5e-f1a7-4873-aa64-a606a0e481cd",
            "source_id": "6cd219cc-3203-4602-88bd-d3639f86fb37",
            "target_id": "70447169-9264-41dc-b8e9-50523f8368c1"
        },
        {
            "id": "bfe3db02-f93f-4d91-bd78-beccee980175",
            "source_id": "45199aa0-1556-4b94-8940-3ba30aa08e38",
            "target_id": "f129934f-53d2-49f6-8feb-9afaff9aabcf"
        },
        {
            "id": "3c2f9db7-3b78-4bc0-b990-3d0eacdca90e",
            "source_id": "51775eb3-70c0-4d8e-95a5-b34ffba8a280",
            "target_id": "45199aa0-1556-4b94-8940-3ba30aa08e38"
        }
    ],
    "metadata": {
        "core": {
            "analyst_email": "siwells@gmail.com",
            "analyst_name": "Simon Wells",
            "created": "2019-04-22T23:52:30",
            "description": "An example SADFace document showing an argument analysis of the Hangback cycle safety campaign from the STCD corpora.",
            "edited": "2019-04-22T23:52:30",
            "id": "42e56df7-4074-40d8-8ea1-4fca5321dd31",
            "notes": "This is incomplete because the analysis in Pangbourne & Wells (2018) has much more argumenative content.",
            "title": "Hangback Example",
            "version": "0.2"
        }
    },
    "nodes": [
        {
            "id": "ae3f0c7f-9f69-4cab-9db3-3b9c46f56e09",
            "metadata": {},
            "sources": [],
            "text": "The 'Hang Back' campaign video should not have been published, and should be withdrawn.",
            "type": "atom"
        },
        {
            "id": "70447169-9264-41dc-b8e9-50523f8368c1",
            "metadata": {},
            "name": "support",
            "type": "scheme"
        },
        {
            "id": "f129934f-53d2-49f6-8feb-9afaff9aabcf",
            "metadata": {},
            "sources": [],
            "text": "The 'Hang Back' campaign was the wrong campaign to run",
            "type": "atom"
        },
        {
            "id": "6cd219cc-3203-4602-88bd-d3639f86fb37",
            "metadata": {},
            "sources": [],
            "text": "The 'Hang Back' advert does not clearly express the intended message",
            "type": "atom"
        },
        {
            "id": "45199aa0-1556-4b94-8940-3ba30aa08e38",
            "metadata": {},
            "name": "conflict",
            "type": "scheme"
        },
        {
            "id": "51775eb3-70c0-4d8e-95a5-b34ffba8a280",
            "metadata": {},
            "sources": [],
            "text": "Road users have a responsibility to make our roads safer by being more vigilant.",
            "type": "atom"
        }
    ],
    "resources": []
}
